{
  "gfx": {
    "main_gif": "https://media.giphy.com/media/v1.Y2lkPTc5MGI3NjExNHJpY2NqZ3R4Z3R4Z3R4Z3R4Z3R4Z3R4Z3R4Z3R4Z3R4Z3ImZXA9djFfaW50ZXJuYWxfZ2lmX2J5X2lkJmN0PWc/26tOZ42Mg6pbMubM4/giphy.gif",
    "color": "#FF4500"
  },
  "prices": {
    "zimne_ognie": 25,
    "piccolo": 150,
    "szampan_procenty": 1200,
    "wyrzutnia_pro": 10000,
    "prestige_req": 1000000
  },
  "boosts": {
    "zimne_ognie": 1,
    "piccolo": 5,
    "szampan_procenty": 25,
    "wyrzutnia_pro": 150,
    "prestige_multiplier": 10
  },
  "drop": {
    "reward": 5000,
    "required_clicks": 1,
    "chance": 0.02
  }
}